spark_expectations/__init__.py
spark_expectations/config/__init__.py
spark_expectations/config/spark-expectations-default-config.yaml
spark_expectations/config/user_config.py
spark_expectations/config/templates/advanced_email_alert_template.jinja
spark_expectations/config/templates/basic_email_alert_template.jinja
spark_expectations/config/templates/custom_email_alert_template.jinja
spark_expectations/core/__init__.py
spark_expectations/core/context.py
spark_expectations/core/exceptions.py
spark_expectations/core/expectations.py
spark_expectations/notifications/__init__.py
spark_expectations/notifications/plugins/__init__.py
spark_expectations/notifications/plugins/base_notification.py
spark_expectations/notifications/plugins/email.py
spark_expectations/notifications/plugins/pagerduty.py
spark_expectations/notifications/plugins/slack.py
spark_expectations/notifications/plugins/teams.py
spark_expectations/notifications/plugins/zoom.py
spark_expectations/notifications/push/__init__.py
spark_expectations/notifications/push/alert.py
spark_expectations/notifications/push/spark_expectations_notify.py
spark_expectations/secrets/__init__.py
spark_expectations/sinks/__init__.py
spark_expectations/sinks/plugins/__init__.py
spark_expectations/sinks/plugins/base_writer.py
spark_expectations/sinks/plugins/kafka_writer.py
spark_expectations/sinks/utils/__init__.py
spark_expectations/sinks/utils/collect_statistics.py
spark_expectations/sinks/utils/report.py
spark_expectations/sinks/utils/writer.py
spark_expectations/utils/__init__.py
spark_expectations/utils/actions.py
spark_expectations/utils/reader.py
spark_expectations/utils/regulate_flow.py
spark_expectations/utils/udf.py
spark_expectations/utils/validate_rules.py
spark_expectations-2.8.1.dist-info/METADATA
spark_expectations-2.8.1.dist-info/WHEEL
spark_expectations-2.8.1.dist-info/licenses/LICENSE
spark_expectations-2.8.1.dist-info/RECORD
