Metadata-Version: 2.4
Name: spark-expectations
Version: 2.8.1
Summary: This project helps us to run Data Quality Rules in flight while spark job is being run
Author-email: Ashok Singamaneni <ashok.singamaneni@nike.com>
License-File: LICENSE
Classifier: Programming Language :: Python
Requires-Python: <=3.13,>=3.9
Requires-Dist: pluggy>=1
Requires-Dist: requests>=2.28.1
Requires-Dist: sqlglot<23.0,>=21.0
Provides-Extra: mkdocstrings
Requires-Dist: mkdocstrings[python]==0.27.0; extra == 'mkdocstrings'
Provides-Extra: pyspark
Requires-Dist: pyspark[connect]<=4.0.0,>=3.0.0; extra == 'pyspark'
